fc_mxr_bigdata.py
mxr_bigdata2-1.0.0.dist-info/METADATA
mxr_bigdata2-1.0.0.dist-info/WHEEL
mxr_bigdata2-1.0.0.dist-info/top_level.txt
mxr_bigdata2-1.0.0.dist-info/RECORD
