Metadata-Version: 2.1
Name: mxr-bigdata2
Version: 1.0.0
Summary: 大数据1
Home-page: UNKNOWN
Author: 大数据1
Author-email: mxr@bigdata.com
License: UNKNOWN
Platform: UNKNOWN
